pyinj/__init__.py
pyinj/analyzer.py
pyinj/container.py
pyinj/contextual.py
pyinj/defaults.py
pyinj/exceptions.py
pyinj/injection.py
pyinj/metaclasses.py
pyinj/py.typed
pyinj/tokens.py
pyinj/types.py
pyinj/protocols/__init__.py
pyinj/protocols/resolvable.py
pyinj/protocols/resources.py
pyinj-1.3.0.dist-info/METADATA
pyinj-1.3.0.dist-info/WHEEL
pyinj-1.3.0.dist-info/licenses/LICENSE
pyinj-1.3.0.dist-info/licenses/LICENSE.md
pyinj-1.3.0.dist-info/licenses/NOTICE
pyinj-1.3.0.dist-info/RECORD
