Metadata-Version: 2.4
Name: pyinj
Version: 1.3.0
Summary: DEPRECATED: PyInj has been renamed to 'injx'. Please migrate to the new package.
Project-URL: Homepage, https://github.com/qriusglobal/pyinj
Project-URL: Repository, https://github.com/qriusglobal/pyinj
Project-URL: Documentation, https://github.com/qriusglobal/pyinj#readme
Project-URL: Bug Tracker, https://github.com/qriusglobal/pyinj/issues
Project-URL: Changelog, https://github.com/qriusglobal/pyinj/releases
Project-URL: CI, https://github.com/qriusglobal/pyinj/actions
Author-email: Qrius Global <mishal@qrius.global>
License: LGPL-3.0-or-later WITH DI-exception OR Commercial-Attribution
License-File: LICENSE
License-File: LICENSE.md
License-File: NOTICE
Keywords: async,dependency-injection,di,ioc,python3.13,type-safe
Classifier: Development Status :: 7 - Inactive
Classifier: Framework :: AsyncIO
Classifier: Intended Audience :: Developers
Classifier: License :: OSI Approved :: GNU Lesser General Public License v3 or later (LGPLv3+)
Classifier: Operating System :: OS Independent
Classifier: Programming Language :: Python :: 3 :: Only
Classifier: Programming Language :: Python :: 3.13
Classifier: Topic :: Software Development :: Libraries
Classifier: Typing :: Typed
Requires-Python: >=3.13
Provides-Extra: dev
Requires-Dist: aiosqlite>=0.19; extra == 'dev'
Requires-Dist: asyncpg>=0.29; extra == 'dev'
Requires-Dist: httpx>=0.27; extra == 'dev'
Requires-Dist: playwright>=1.44; extra == 'dev'
Requires-Dist: pre-commit>=3.7; extra == 'dev'
Requires-Dist: pytest-asyncio>=0.23; extra == 'dev'
Requires-Dist: pytest>=8.2; extra == 'dev'
Requires-Dist: sqlalchemy>=2.0; extra == 'dev'
